LICENSE
MANIFEST.in
README.md
setup.cfg
setup.py
src/django_search_and_replace.egg-info/PKG-INFO
src/django_search_and_replace.egg-info/SOURCES.txt
src/django_search_and_replace.egg-info/dependency_links.txt
src/django_search_and_replace.egg-info/requires.txt
src/django_search_and_replace.egg-info/top_level.txt
src/search_and_replace/__init__.py
src/search_and_replace/admin.py
src/search_and_replace/apps.py
src/search_and_replace/forms.py
src/search_and_replace/models.py
src/search_and_replace/tests.py
src/search_and_replace/views.py
src/search_and_replace/migrations/__init__.py
src/search_and_replace/static/search_and_replace/css/search_and_replace.css
src/search_and_replace/static/search_and_replace/js/mark-8.11.1.min.js
src/search_and_replace/static/search_and_replace/js/search_and_replace.js
src/search_and_replace/templates/search_and_replace/search_and_replace.html
src/search_and_replace/templatetags/__init__.py
src/search_and_replace/templatetags/search_and_replace_tags.py