Metadata-Version: 2.1
Name: django-search-and-replace
Version: 0.0.8
Summary: A search and replace app for django
Home-page: https://github.com/RaphaelKimmig/django-search-and-replace
Author: Raphael Kimmig
Author-email: raphael@ampad.de
License: BSD 3-Clause License
Download-URL: https://github.com/RaphaelKimmig/django-search-and-replace/archive/v0.0.8.tar.gz
Platform: UNKNOWN
Classifier: Framework :: Django
Classifier: Programming Language :: Python :: 3
License-File: LICENSE
